pyoad/__init__.py
pyoad/main.py
pyoad/tests/__init__.py
pyoad/tests/conftest.py
pyoad/tests/test_main.py
pyoad-1.0.2.dist-info/DESCRIPTION.rst
pyoad-1.0.2.dist-info/METADATA
pyoad-1.0.2.dist-info/RECORD
pyoad-1.0.2.dist-info/WHEEL
pyoad-1.0.2.dist-info/metadata.json
pyoad-1.0.2.dist-info/top_level.txt
