Metadata-Version: 2.0
Name: pyoad
Version: 1.0.2
Summary: Spawns an object as a daemon in another process, possibly using another python executable/environment
Home-page: https://github.com/smarie/python-object-as-daemon
Author: Sylvain Marié
Author-email: sylvain.marie@schneider-electric.com
License: BSD 3-Clause
Download-URL: https://github.com/smarie/python-object-as-daemon/tarball/1.0.2
Keywords: spawn object process daemon proxy rpc distribute
Platform: UNKNOWN
Classifier: Development Status :: 5 - Production/Stable
Classifier: Intended Audience :: Developers
Classifier: Topic :: Software Development :: Libraries :: Python Modules
Classifier: License :: OSI Approved :: BSD License
Classifier: Programming Language :: Python :: 3.5
Classifier: Programming Language :: Python :: 3.6
